plone.portlet.collection-4.0.5-py3.13-nspkg.pth
plone/portlet/collection/__init__.py
plone/portlet/collection/collection.pt
plone/portlet/collection/collection.py
plone/portlet/collection/configure.zcml
plone/portlet/collection/testing.py
plone/portlet/collection/profiles/default/metadata.xml
plone/portlet/collection/profiles/default/portlets.xml
plone/portlet/collection/tests/__init__.py
plone/portlet/collection/tests/functional.txt
plone/portlet/collection/tests/test_functional_doctest.py
plone/portlet/collection/tests/test_portlet_collection.py
plone_portlet_collection-4.0.5.dist-info/METADATA
plone_portlet_collection-4.0.5.dist-info/WHEEL
plone_portlet_collection-4.0.5.dist-info/namespace_packages.txt
plone_portlet_collection-4.0.5.dist-info/top_level.txt
plone_portlet_collection-4.0.5.dist-info/RECORD
